{"path":"docs/compass/0.1/introduction/overview","templateID":1,"sharedPropsHashes":{},"localProps":{"markdown":"# コンパス概要\n<!-- # Compass overview -->\n\n**コンパスはコーディネーターのオープンソース実装です。テストおよび開発の目的で、コンパスを使用して独自のIOTAネットワークを運用することができます。**\n<!-- **Compass is an open-source implementation of the Coordinator. You can use Compass to run your own IOTA network for testing and development purposes.** -->\n\nIOTAは、トランザクションを検証して、そのトランザクションを格納するノードの分散ネットワークです。ノードがアドレスの残高を更新する前に、更新された残高につながるすべてのトランザクションについて合意に達する必要があります。ノードがトランザクションに関して合意に達すると、それらのトランザクションは確定されます。\n<!-- IOTA is a distributed network of nodes that validate transactions and store them. Before nodes can update the balance of an address, they must reach a consensus on any transactions that lead to the updated balance. When nodes reach a consensus, on transactions, those transactions are confirmed. -->\n\nIOTA Mainnet上で、[コーディネーター](/docs/the-tangle/0.1/concepts/the-coordinator)はマイルストーンを含むバンドルを作成、署名、および送信します。Mainnet上のノードは、合意に達するためにマイルストーンを使用します。マイルストーンによって参照され承認されたトランザクションはすべて確定されます。\n<!-- On the IOTA Mainnet, the [Coordinator](/docs/the-tangle/0.1/concepts/the-coordinator) creates, signs, and sends bundles that contain milestones. The nodes on this network use these milestone to reach a consensus. Any transaction that's referenced and approved by a milestone is confirmed. -->\n\nコンパスはコーディネーターのオープンソース実装です。コンパスを使用すると、自分のIOTAネットワーク内のノードが、コーディネーターのマイルストーンではなくコンパスのマイルストーンを使って合意に達することができます。\n<!-- Compass is an open-source implementation of the Coordinator. You can use Compass to allow the nodes in your own IOTA network to reach a consensus on Compass' milestones instead of the Coordinator's ones. -->\n\nノードが合意に達することを許可するには、コンパスマイルストーンを認識するようにノードを設定する必要があります。その後、定期的に1つのノードにマイルストーンを送信するようにコンパスを設定できます。\n<!-- To allow your nodes to reach a consensus, you must configure your nodes to recognize Compass milestones. Then, you can configure Compass to send milestones to one of your nodes at regular intervals. -->\n\n:::info:\n[独自のIOTAネットワークを作成する](../how-to-guides/create-an-iota-network.md)。\n:::\n<!-- :::info: -->\n<!-- [Create your own IOTA network](../how-to-guides/create-an-iota-network.md). -->\n<!-- ::: -->\n\n## リポジトリ\n<!-- ## Repository -->\n\n[GithubのCompassソースコード](https://github.com/iotaledger/compass)に行く。\n<!-- Go to the Compass source code on [Github](https://github.com/iotaledger/compass) -->\n\n## 参考文献\n<!-- ## Further reading -->\n\n- [タングルおよびその他のプロトコル機能について議論しているIOTA論文](https://www.iota.org/research/academic-papers)\n<!-- - [IOTA papers discussing the Tangle and other protocol features](https://www.iota.org/research/academic-papers) -->\n- [コーディネーターの削除について議論する一連の投稿](https://blog.iota.org/coordinator-part-1-the-path-to-coordicide-ee4148a8db08)\n<!-- - [A series of posts discussing the removal of the Coordinator](https://blog.iota.org/coordinator-part-1-the-path-to-coordicide-ee4148a8db08) -->\n","title":"概要 | 序説 | コンパス"}}
