{"path":"docs/node-software/0.1/iri/references/data-in-the-ledger","templateID":1,"sharedPropsHashes":{},"localProps":{"markdown":"# 台帳内のデータ構造\n<!-- # Data in the ledger -->\n\n**この表には，有効なトランザクションごとに IRI ノードが自身の台帳に追加するデータが含まれています．**\n<!-- **This table contains the data that an IRI node appends to its ledger for each valid transaction.** -->\n\n| **カラム** | **データ** | **説明** |\n| :--------: | :--------: | :------- |\n| `transaction` | トランザクションハッシュ | トランザクションのトランザクションバイト |\n| `transactionMetadata` | トランザクションハッシュ | トランザクションのデータとIRIによって追加された追加のメタデータ |\n| `milestone` | マイルストーンインデックス | トランザクションを承認するマイルストーンバンドル内の末尾トランザクションハッシュとトランザクションのインデックスの両方 |\n| `stateDiffs` | マイルストーンハッシュ | マイルストーンが台帳で確定したアドレスの残高の変更 |\n| `address` | アドレスハッシュ | アドレスの残高を変更したトランザクションハッシュのリスト |\n| `approvees` | トランザクションハッシュ | トランザクションを直接参照するトランザクションのトランザクションハッシュ |\n| `bundle` | バンドルハッシュ | トランザクションのバンドルに属するトランザクションハッシュのリスト |\n| `obsoleteTag` | 痕跡タグ | バンドルエッセンス（署名される部分）の一部である，同じ廃止タグを持つトランザクションハッシュのリスト |\n| `tag` | タグ | 同じタグを持つトランザクションハッシュのリスト．このタグはバンドルエッセンスの一部ではありません（このタグは署名されない部分）． |\n\n## トランザクションメタデータ\n<!-- ## Transaction metadata -->\n\n次の表に，IRI ノードが `transactionMetadata` カラムに追加するメタデータを示します．\n<!-- The following table contains the metadata that an IRI node appends to the `transactionMetadata` column. -->\n\n| **フィールド** | **データ** | **説明** |\n| :------------- | :--------- | :------- |\n| `validity` | -1か0か1 | この値は[バンドルバリデータ](../concepts/transaction-validation.md#bundle-validator)によって設定されます．値の意味は-1（無効），1（有効），0（不明）です． |\n| `type` | `PREFILLED_SLOT` か `FILLED_SLOT` | `PREFILLED_SLOT` はトランザクションハッシュが存在することを意味しますが，ノードは自身の台帳にそのトランザクションハッシュを持っていません．`FILLED_SLOT` は，ノードの台帳にトランザクションハッシュがあることを意味します． |\n| `arrivalTime` | integer | この値は，IRI ノードがトランザクションを受信した時間（ミリ秒）です． |\n| `parsed` | boolean | この値は，メタデータがパースされたかどうかを確認するために内部的に使用されます． |\n| `solid` | boolean | このトランザクションとこのトランザクションが参照するすべてのトランザクションの履歴が台帳にある場合にのみ，この値は `true` に設定されます． |\n| `sender` | URL か IP アドレス | トランザクションを送信したノードの URL または IP アドレス |\n| `snapshot` | マイルストーンインデックス | トランザクションを確定した最初のマイルストーントランザクションのマイルストーンインデックス |\n","title":"台帳内のデータ構造 | 参考文献 | IRI | ノードSW"}}
